textual_mastermind/__init__.py
textual_mastermind/app.py
textual_mastermind/app_config.py
textual_mastermind/bindings.py
textual_mastermind/config.toml
textual_mastermind/constants.py
textual_mastermind/game.py
textual_mastermind/locale/messages.pot
textual_mastermind/locale/pl/LC_MESSAGES/messages.mo
textual_mastermind/locale/pl/LC_MESSAGES/messages.po
textual_mastermind/styles.tcss
textual_mastermind/widgets/__init__.py
textual_mastermind/widgets/board.py
textual_mastermind/widgets/panel.py
textual_mastermind-3.0.3.dist-info/WHEEL
textual_mastermind-3.0.3.dist-info/entry_points.txt
textual_mastermind-3.0.3.dist-info/METADATA
textual_mastermind-3.0.3.dist-info/RECORD
