Metadata-Version: 2.3
Name: textual-mastermind
Version: 3.0.3
Summary: Mastermind game built with Textual
Author: Rafal Padkowski
Author-email: Rafal Padkowski <rafaelp@poczta.onet.pl>
Requires-Dist: textual>=6.6.0
Requires-Dist: textual-utils>=2.1.1
Requires-Python: >=3.13
